{
    "countMalformed": 9,
    "offset": 0,
    "results": [
                {
                "name": "Testfile.rtf",
                "path": "/Shared/UploadTest/Testfile.rtf",
                "type": "application/rtf",
                "size": 324,
                "snippet": "Test",
                "entry_id": "22ab9532-47a0-4f88-8910-d3b848ff37e3",
                "group_id": "559d172d-7421-4ac9-a5d0-de6482ca6adf",
                "last_modified": "2016-11-21T14:11:02Z",
                "uploaded_by": "Adam Kędzia",
                "uploaded_by_username": "akedzia",
                "num_versions": 1,
                "snippet_html": "<Bold>Test</Bold>",
                "is_folder": false,
                "custom_properties": []
                },
                {
                "name": "Testfile.rtf",
                "path": "/Shared/Upload Test/Testfile.rtf",
                "type": "application/rtf",
                "size": 324,
                "snippet": "Test",
                "entry_id": "d6d21305-7862-496c-968a-1db18ba3cad2",
                "group_id": "de1dd3d3-e3a1-4f11-9f03-88127b5234bb",
                "last_modified": "2016-11-21T14:37:17Z",
                "uploaded_by": "Adam Kędzia",
                "uploaded_by_username": "akedzia",
                "num_versions": 1,
                "snippet_html": "<Bold>Test</Bold>",
                "is_folder": false,
                "custom_properties": []
                },
                {
                "name": "CreateTest",
                "path": "/Shared/Create Folder Test/CreateTest",
                "is_folder": true
                },
                {
                "name": "UploadTest",
                "path": "/Shared/UploadTest",
                "is_folder": true
                },
                {
                "name": "Answer to the Ultimate Question of Life, the Universe, and Everything   ☃☃☃.txt",
                "path": "/Shared/Download Test/Answer to the Ultimate Question of Life, the Universe, and Everything   ☃☃☃.txt",
                "type": "text/plain",
                "size": 10584,
                "snippet": "42☃\n42☃\n42☃\n42☃\n42☃\n42☃\n42☃\n42☃\n42☃\n42☃\n42☃\n42☃\n42☃\n42☃\n42☃\n42☃\n42☃\n42☃\n42☃\n42☃\n42☃\n42☃\n42☃\n42☃\n42☃\n42☃\n42☃\n42☃\n42☃\n42☃\n42☃\n42☃\n42☃\n42☃\n42☃\n42☃\n42☃\n42",
                "entry_id": "4835face-64d3-4cc2-8125-5e1de8717a27",
                "group_id": "09cac068-2a58-437f-810b-de52e7589f03",
                "last_modified": "2016-11-17T00:49:12Z",
                "uploaded_by": "Mateusz Sikora",
                "uploaded_by_username": "msikora",
                "num_versions": 1,
                "snippet_html": "42☃\n42☃\n42☃\n42☃\n42☃\n42☃\n42☃\n42☃\n42☃\n42☃\n42☃\n42☃\n42☃\n42☃\n42☃\n42☃\n42☃\n42☃\n42☃\n42☃\n42☃\n42☃\n42☃\n42☃\n42☃\n42☃\n42☃\n42☃\n42☃\n42☃\n42☃\n42☃\n42☃\n42☃\n42☃\n42☃\n42☃\n42",
                "is_folder": false,
                "custom_properties": []
                },
                {
                "name": "I'm a squirrel!.jpg",
                "path": "/Shared/Listing  Test ☃☃☃/I'm a squirrel!.jpg",
                "type": "image/jpeg",
                "size": 43235,
                "snippet": "",
                "entry_id": "a7115388-469e-4dee-9063-0ad156bfad03",
                "group_id": "e0d23c54-7673-40d9-b2ff-434996011713",
                "last_modified": "2014-04-29T20:24:42Z",
                "uploaded_by": "Mateusz Sikora",
                "uploaded_by_username": "msikora",
                "num_versions": 1,
                "snippet_html": "",
                "is_folder": false,
                "custom_properties": []
                },
                {
                "name": "upload me.txt",
                "path": "/Shared/Upload Test/upload me.txt",
                "type": "text/plain",
                "size": 10584,
                "snippet": "42☃\n42☃\n42☃\n42☃\n42☃\n42☃\n42☃\n42☃\n42☃\n42☃\n42☃\n42☃\n42☃\n42☃\n42☃\n42☃\n42☃\n42☃\n42☃\n42☃\n42☃\n42☃\n42☃\n42☃\n42☃\n42☃\n42☃\n42☃\n42☃\n42☃\n42☃\n42☃\n42☃\n42☃\n42☃\n42☃\n42☃\n42",
                "entry_id": "5808cc9c-2ba5-4649-abd3-e4ea7f07566a",
                "group_id": "57bf5204-5fdb-401a-ab11-496719616864",
                "last_modified": "2016-11-18T11:25:47Z",
                "uploaded_by": "Mateusz Sikora",
                "uploaded_by_username": "msikora",
                "num_versions": 3,
                "snippet_html": "42☃\n42☃\n42☃\n42☃\n42☃\n42☃\n42☃\n42☃\n42☃\n42☃\n42☃\n42☃\n42☃\n42☃\n42☃\n42☃\n42☃\n42☃\n42☃\n42☃\n42☃\n42☃\n42☃\n42☃\n42☃\n42☃\n42☃\n42☃\n42☃\n42☃\n42☃\n42☃\n42☃\n42☃\n42☃\n42☃\n42☃\n42",
                "is_folder": false,
                "custom_properties": []
                },
                {
                "name": "productive.jpg",
                "path": "/Shared/Download Test/productive.jpg",
                "type": "image/jpeg",
                "size": 87641,
                "snippet": "",
                "entry_id": "68830b2b-615b-44aa-98d3-c81b7af88e14",
                "group_id": "479a3270-3718-4b81-afe3-90672b3314a3",
                "last_modified": "2016-08-31T12:56:56Z",
                "uploaded_by": "Adam Kędzia",
                "uploaded_by_username": "akedzia",
                "num_versions": 1,
                "snippet_html": "",
                "is_folder": false,
                "custom_properties": []
                },
                {
                "name": "File.txt",
                "path": "/Shared/Create Link Test/File.txt",
                "type": "text/plain",
                "size": 5,
                "snippet": "42",
                "entry_id": "f34d51f7-2cdd-418c-9ba6-d18d05627e60",
                "group_id": "6aaf6102-ea3b-46b6-9335-7b977256d951",
                "last_modified": "2016-11-18T17:42:24Z",
                "uploaded_by": "Mateusz Sikora",
                "uploaded_by_username": "msikora",
                "num_versions": 1,
                "snippet_html": "42",
                "is_folder": false,
                "custom_properties": []
                }
                ],
    "hasMore": false,
    "total_count": 9
}
